minesweeper/__init__.py
minesweeper/__main__.py
minesweeper/gui.py
minesweeper/user_interface.py
minesweeper/user_interface_board.py
minesweeper/user_interface_face.py
minesweeper/user_interface_frame.py
minesweeper/user_interface_score.py
minesweeper/util.py
pygame_minesweeper-1.0.11.dist-info/LICENSE
pygame_minesweeper-1.0.11.dist-info/METADATA
pygame_minesweeper-1.0.11.dist-info/WHEEL
pygame_minesweeper-1.0.11.dist-info/entry_points.txt
pygame_minesweeper-1.0.11.dist-info/top_level.txt
pygame_minesweeper-1.0.11.dist-info/RECORD
