Metadata-Version: 2.1
Name: pygame-minesweeper
Version: 1.0.11
Summary: Minesweeper game implemented in python using pygame
Home-page: https://github.com/andreasisnes/Elitekollektivet.Minesweeper
Author: Andreas Isnes Nilsen
Author-email: andreas.isnes@gmail.com
License: UNKNOWN
Platform: UNKNOWN
Classifier: Programming Language :: Python :: 3
Classifier: License :: OSI Approved :: MIT License
Classifier: Operating System :: OS Independent
Requires-Dist: pygame
Requires-Dist: pygame-minesweeper-core
Requires-Dist: pygame-minesweeper-sprites
Requires-Dist: appdirs
